akita_flask/__init__.py
akita_flask/testing.py
akita_flask-0.0.4.dist-info/LICENSE
akita_flask-0.0.4.dist-info/METADATA
akita_flask-0.0.4.dist-info/WHEEL
akita_flask-0.0.4.dist-info/top_level.txt
akita_flask-0.0.4.dist-info/RECORD
