Metadata-Version: 2.1
Name: akita-flask
Version: 0.0.4
Summary: Utilities for connecting Akita to Django
Home-page: https://github.com/akitasoftware/akita-flask
Author: Cole Schlesinger
Author-email: cole@akitasoftware.com
License: UNKNOWN
Platform: UNKNOWN
Classifier: Programming Language :: Python :: 3
Classifier: License :: OSI Approved :: Apache Software License
Classifier: Operating System :: OS Independent
Requires-Python: >=3.6
Requires-Dist: akita-har
Requires-Dist: flask
